noll/__init__.py
noll/noll.py
noll-0.1.0.dist-info/METADATA
noll-0.1.0.dist-info/WHEEL
noll-0.1.0.dist-info/RECORD
