Metadata-Version: 2.1
Name: noll
Version: 0.1.0
Summary: Nothing. Nil. Nada.
Home-page: https://gitlab.com/deepadmax/noll
Author: Maximillian Strand
Author-email: maxi@millian.se
Requires-Python: >=3.9,<4.0
Classifier: Programming Language :: Python :: 3
Classifier: Programming Language :: Python :: 3.9
Classifier: Programming Language :: Python :: 3.10
Classifier: Programming Language :: Python :: 3.11
Project-URL: Repository, https://gitlab.com/deepadmax/noll
